superexacttestpy/__init__.py
superexacttestpy/pl/__init__.py
superexacttestpy/pl/basic.py
superexacttestpy/tl/__init__.py
superexacttestpy/tl/basic.py
superexacttestpy-0.0.1.dist-info/LICENSE
superexacttestpy-0.0.1.dist-info/WHEEL
superexacttestpy-0.0.1.dist-info/METADATA
superexacttestpy-0.0.1.dist-info/RECORD
